arattai/ArattaiBot.py
arattai/__init__.py
arattai/auth/__init__.py
arattai/auth/qr_login.py
arattai/auth/session_manager.py
arattai/auth/token_login.py
arattai/models/__init__.py
arattai/models/bot.py
arattai/models/chats.py
arattai/models/message_manager.py
arattai-0.3.1.dist-info/METADATA
arattai-0.3.1.dist-info/WHEEL
arattai-0.3.1.dist-info/top_level.txt
arattai-0.3.1.dist-info/RECORD
