Metadata-Version: 2.4
Name: arattai
Version: 0.3.1
Summary: Python library for Arattai messaging API.
Author: Vivek Kumar
Dynamic: author
Dynamic: description
Dynamic: description-content-type
Dynamic: summary
